pdfunlock/__init__.py
pdfunlock/__main__.py
pdfunlock/_version.py
pdfunlock/app.py
pdfunlock/console.py
pdfunlock-0.1.0.dist-info/LICENSE.md
pdfunlock-0.1.0.dist-info/METADATA
pdfunlock-0.1.0.dist-info/WHEEL
pdfunlock-0.1.0.dist-info/entry_points.txt
pdfunlock-0.1.0.dist-info/top_level.txt
pdfunlock-0.1.0.dist-info/RECORD
