Metadata-Version: 2.1
Name: pdfunlock
Version: 0.1.0
Summary: A simple command-line tool to unlock PDF files with only an edit password.
Author: Andrew Powers-Holmes
Author-email: Andrew Powers-Holmes <aholmes@omnom.net>
Maintainer: Andrew Powers-Holmes
Maintainer-email: Andrew Powers-Holmes <aholmes@omnom.net>
License: # GNU GENERAL PUBLIC LICENSE
Project-URL: documentation, https://github.com/neggles/pdfunlock/wiki
Project-URL: repository, https://github.com/neggles/pdfunlock
Project-URL: issue-tracker, https://github.com/neggles/pdfunlock/issues
Keywords: pdf,unlock,password,command-line,typer
Classifier: Development Status :: 4 - Beta
Classifier: Programming Language :: Python
Requires-Python: >=3.9
License-File: LICENSE.md
Requires-Dist: typer (<0.8.0,>=0.6.1)
Requires-Dist: colorama (>=0.4.3)
Requires-Dist: shellingham (<2.0.0,>=1.3.0)
Requires-Dist: rich (<14.0.0,>=10.11.0)
Requires-Dist: pikepdf (<8.0.0,>=7.1.0)
Provides-Extra: dev
Requires-Dist: black (>=22.3.0) ; extra == 'dev'
Requires-Dist: flake8 (>=4.0.1) ; extra == 'dev'
Requires-Dist: setuptools-scm (>=7.0.0) ; extra == 'dev'
Requires-Dist: mypy (>=0.981) ; extra == 'dev'
Requires-Dist: build (>=0.10.0) ; extra == 'dev'
Requires-Dist: twine (>=4.0.2) ; extra == 'dev'
